{"$type":"List`1","$values":[{"$id":"1","$type":"ProjectOptionEntry","key":"NetworkCollapsed","context":"{2232342-3983}","value":false},{"$id":"2","$type":"ProjectOptionEntry","key":"NetworkCollapsed","context":"{2232342-4002}","value":false},{"$id":"3","$type":"ProjectOptionEntry","key":"RestoreNetworkStates","context":"{2232321-3980}","value":true},{"$id":"4","$type":"ProjectOptionEntry","key":"RestoreNetworkStates","context":"{2232321-3878}","value":true},{"$id":"5","$type":"ProjectOptionEntry","key":"NetworkCollapsed","context":"{2232342-6225}","value":false},{"$id":"6","$type":"ProjectOptionEntry","key":"RestoreNetworkStates","context":"{2232321-6222}","value":true},{"$id":"7","$type":"ProjectOptionEntry","key":"NetworkCollapsed","context":"{2232342-6227}","value":false},{"$id":"8","$type":"ProjectOptionEntry","key":"NetworkCollapsed","context":"{2232342-4008}","value":false},{"$id":"9","$type":"ProjectOptionEntry","key":"NetworkCollapsed","context":"{2232342-6236}","value":false},{"$id":"10","$type":"ProjectOptionEntry","key":"RestoreNetworkStates","context":"{2232321-6233}","value":true},{"$id":"11","$type":"ProjectOptionEntry","key":"NetworkCollapsed","context":"{2232342-6237}","value":false},{"$id":"12","$type":"ProjectOptionEntry","key":"NetworkCollapsed","context":"{2232342-6239}","value":false},{"$id":"13","$type":"ProjectOptionEntry","key":"NetworkCollapsed","context":"{2232342-3927}","value":false},{"$id":"14","$type":"ProjectOptionEntry","key":"NetworkCollapsed","context":"{2232342-3928}","value":false},{"$id":"15","$type":"ProjectOptionEntry","key":"NetworkCollapsed","context":"{2232342-3930}","value":false},{"$id":"16","$type":"ProjectOptionEntry","key":"RestoreNetworkStates","context":"{2232321-3924}","value":true},{"$id":"17","$type":"ProjectOptionEntry","key":"NetworkCollapsed","context":"{2232342-7306}","value":false},{"$id":"18","$type":"ProjectOptionEntry","key":"NetworkCollapsed","context":"{2232342-7372}","value":false},{"$id":"19","$type":"ProjectOptionEntry","key":"NetworkCollapsed","context":"{2232342-3971}","value":false},{"$id":"20","$type":"ProjectOptionEntry","key":"LastSelection@Siemens.Simatic.PlcLanguages.PLFrame.BasicLanguageEditor","context":"{2232321-3878}","value":{"$id":"21","$type":"SessionState","NetworkStates":{"$id":"22","$type":"Dictionary`2","2":5},"FocusedComponent":4,"ComponentUndoState":{"$id":"23","$type":"SessionDataUndo","CaretPositionRC":"24, 13"}}},{"$id":"24","$type":"ProjectOptionEntry","key":"NetworkCollapsed","context":"{2232342-8280}","value":false},{"$id":"25","$type":"ProjectOptionEntry","key":"NetworkCollapsed","context":"{2232342-8281}","value":false},{"$id":"26","$type":"ProjectOptionEntry","key":"NetworkCollapsed","context":"{2232342-10357}","value":false},{"$id":"27","$type":"ProjectOptionEntry","key":"NetworkCollapsed","context":"{2232342-10358}","value":false},{"$id":"28","$type":"ProjectOptionEntry","key":"NetworkCollapsed","context":"{2232342-10359}","value":false},{"$id":"29","$type":"ProjectOptionEntry","key":"NetworkCollapsed","context":"{2232342-10360}","value":false},{"$id":"30","$type":"ProjectOptionEntry","key":"NetworkCollapsed","context":"{2232342-10361}","value":false},{"$id":"31","$type":"ProjectOptionEntry","key":"RestoreNetworkStates","context":"{2232321-10344}","value":true},{"$id":"32","$type":"ProjectOptionEntry","key":"NetworkCollapsed","context":"{2232342-10362}","value":false},{"$id":"33","$type":"ProjectOptionEntry","key":"NetworkCollapsed","context":"{2232342-10363}","value":false},{"$id":"34","$type":"ProjectOptionEntry","key":"NetworkCollapsed","context":"{2232342-10364}","value":false},{"$id":"35","$type":"ProjectOptionEntry","key":"NetworkCollapsed","context":"{2232342-10365}","value":false}]}